<?xml version="1.0" encoding="UTF-8"?>
<!DOCTYPE mapper PUBLIC "-//mybatis.org//DTD Mapper 3.0//EN" "http://mybatis.org/dtd/mybatis-3-mapper.dtd">
<mapper namespace="mbg.dao.BitterMapper">
  <resultMap id="BaseResultMap" type="mbg.model.Bitter">
    <!--
      WARNING - @mbggenerated
      This element is automatically generated by MyBatis Generator, do not modify.
      This element was generated on Sat Aug 03 23:23:36 CST 2019.
    -->
    <id column="id" jdbcType="INTEGER" property="id" />
    <result column="username" jdbcType="VARCHAR" property="username" />
    <result column="password" jdbcType="VARCHAR" property="password" />
    <result column="first_name" jdbcType="VARCHAR" property="firstName" />
    <result column="last_name" jdbcType="VARCHAR" property="lastName" />
    <result column="email" jdbcType="VARCHAR" property="email" />
  </resultMap>
  <sql id="Example_Where_Clause">
    <!--
      WARNING - @mbggenerated
      This element is automatically generated by MyBatis Generator, do not modify.
      This element was generated on Sat Aug 03 23:23:36 CST 2019.
    -->
    <where>
      <foreach collection="oredCriteria" item="criteria" separator="or">
        <if test="criteria.valid">
          <trim prefix="(" prefixOverrides="and" suffix=")">
            <foreach collection="criteria.criteria" item="criterion">
              <choose>
                <when test="criterion.noValue">
                  and ${criterion.condition}
                </when>
                <when test="criterion.singleValue">
                  and ${criterion.condition} #{criterion.value}
                </when>
                <when test="criterion.betweenValue">
                  and ${criterion.condition} #{criterion.value} and #{criterion.secondValue}
                </when>
                <when test="criterion.listValue">
                  and ${criterion.condition}
                  <foreach close=")" collection="criterion.value" item="listItem" open="(" separator=",">
                    #{listItem}
                  </foreach>
                </when>
              </choose>
            </foreach>
          </trim>
        </if>
      </foreach>
    </where>
  </sql>
  <sql id="Update_By_Example_Where_Clause">
    <!--
      WARNING - @mbggenerated
      This element is automatically generated by MyBatis Generator, do not modify.
      This element was generated on Sat Aug 03 23:23:36 CST 2019.
    -->
    <where>
      <foreach collection="example.oredCriteria" item="criteria" separator="or">
        <if test="criteria.valid">
          <trim prefix="(" prefixOverrides="and" suffix=")">
            <foreach collection="criteria.criteria" item="criterion">
              <choose>
                <when test="criterion.noValue">
                  and ${criterion.condition}
                </when>
                <when test="criterion.singleValue">
                  and ${criterion.condition} #{criterion.value}
                </when>
                <when test="criterion.betweenValue">
                  and ${criterion.condition} #{criterion.value} and #{criterion.secondValue}
                </when>
                <when test="criterion.listValue">
                  and ${criterion.condition}
                  <foreach close=")" collection="criterion.value" item="listItem" open="(" separator=",">
                    #{listItem}
                  </foreach>
                </when>
              </choose>
            </foreach>
          </trim>
        </if>
      </foreach>
    </where>
  </sql>
  <sql id="Base_Column_List">
    <!--
      WARNING - @mbggenerated
      This element is automatically generated by MyBatis Generator, do not modify.
      This element was generated on Sat Aug 03 23:23:36 CST 2019.
    -->
    id, username, password, first_name, last_name, email
  </sql>
  <select id="selectByExample" parameterType="mbg.model.BitterExample" resultMap="BaseResultMap">
    <!--
      WARNING - @mbggenerated
      This element is automatically generated by MyBatis Generator, do not modify.
      This element was generated on Sat Aug 03 23:23:36 CST 2019.
    -->
    select
    <if test="distinct">
      distinct
    </if>
    <include refid="Base_Column_List" />
    from Bitter
    <if test="_parameter != null">
      <include refid="Example_Where_Clause" />
    </if>
    <if test="orderByClause != null">
      order by ${orderByClause}
    </if>
  </select>
  <select id="selectByPrimaryKey" parameterType="java.lang.Integer" resultMap="BaseResultMap">
    <!--
      WARNING - @mbggenerated
      This element is automatically generated by MyBatis Generator, do not modify.
      This element was generated on Sat Aug 03 23:23:36 CST 2019.
    -->
    select 
    <include refid="Base_Column_List" />
    from Bitter
    where id = #{id,jdbcType=INTEGER}
  </select>
  <delete id="deleteByPrimaryKey" parameterType="java.lang.Integer">
    <!--
      WARNING - @mbggenerated
      This element is automatically generated by MyBatis Generator, do not modify.
      This element was generated on Sat Aug 03 23:23:36 CST 2019.
    -->
    delete from Bitter
    where id = #{id,jdbcType=INTEGER}
  </delete>
  <delete id="deleteByExample" parameterType="mbg.model.BitterExample">
    <!--
      WARNING - @mbggenerated
      This element is automatically generated by MyBatis Generator, do not modify.
      This element was generated on Sat Aug 03 23:23:36 CST 2019.
    -->
    delete from Bitter
    <if test="_parameter != null">
      <include refid="Example_Where_Clause" />
    </if>
  </delete>
  <insert id="insert" parameterType="mbg.model.Bitter">
    <!--
      WARNING - @mbggenerated
      This element is automatically generated by MyBatis Generator, do not modify.
      This element was generated on Sat Aug 03 23:23:36 CST 2019.
    -->
    <selectKey keyProperty="id" order="AFTER" resultType="java.lang.Integer">
      SELECT LAST_INSERT_ID()
    </selectKey>
    insert into Bitter (username, password, first_name, 
      last_name, email)
    values (#{username,jdbcType=VARCHAR}, #{password,jdbcType=VARCHAR}, #{firstName,jdbcType=VARCHAR}, 
      #{lastName,jdbcType=VARCHAR}, #{email,jdbcType=VARCHAR})
  </insert>
  <insert id="insertSelective" parameterType="mbg.model.Bitter">
    <!--
      WARNING - @mbggenerated
      This element is automatically generated by MyBatis Generator, do not modify.
      This element was generated on Sat Aug 03 23:23:36 CST 2019.
    -->
    <selectKey keyProperty="id" order="AFTER" resultType="java.lang.Integer">
      SELECT LAST_INSERT_ID()
    </selectKey>
    insert into Bitter
    <trim prefix="(" suffix=")" suffixOverrides=",">
      <if test="username != null">
        username,
      </if>
      <if test="password != null">
        password,
      </if>
      <if test="firstName != null">
        first_name,
      </if>
      <if test="lastName != null">
        last_name,
      </if>
      <if test="email != null">
        email,
      </if>
    </trim>
    <trim prefix="values (" suffix=")" suffixOverrides=",">
      <if test="username != null">
        #{username,jdbcType=VARCHAR},
      </if>
      <if test="password != null">
        #{password,jdbcType=VARCHAR},
      </if>
      <if test="firstName != null">
        #{firstName,jdbcType=VARCHAR},
      </if>
      <if test="lastName != null">
        #{lastName,jdbcType=VARCHAR},
      </if>
      <if test="email != null">
        #{email,jdbcType=VARCHAR},
      </if>
    </trim>
  </insert>
  <select id="countByExample" parameterType="mbg.model.BitterExample" resultType="java.lang.Integer">
    <!--
      WARNING - @mbggenerated
      This element is automatically generated by MyBatis Generator, do not modify.
      This element was generated on Sat Aug 03 23:23:36 CST 2019.
    -->
    select count(*) from Bitter
    <if test="_parameter != null">
      <include refid="Example_Where_Clause" />
    </if>
  </select>
  <update id="updateByExampleSelective" parameterType="map">
    <!--
      WARNING - @mbggenerated
      This element is automatically generated by MyBatis Generator, do not modify.
      This element was generated on Sat Aug 03 23:23:36 CST 2019.
    -->
    update Bitter
    <set>
      <if test="record.id != null">
        id = #{record.id,jdbcType=INTEGER},
      </if>
      <if test="record.username != null">
        username = #{record.username,jdbcType=VARCHAR},
      </if>
      <if test="record.password != null">
        password = #{record.password,jdbcType=VARCHAR},
      </if>
      <if test="record.firstName != null">
        first_name = #{record.firstName,jdbcType=VARCHAR},
      </if>
      <if test="record.lastName != null">
        last_name = #{record.lastName,jdbcType=VARCHAR},
      </if>
      <if test="record.email != null">
        email = #{record.email,jdbcType=VARCHAR},
      </if>
    </set>
    <if test="_parameter != null">
      <include refid="Update_By_Example_Where_Clause" />
    </if>
  </update>
  <update id="updateByExample" parameterType="map">
    <!--
      WARNING - @mbggenerated
      This element is automatically generated by MyBatis Generator, do not modify.
      This element was generated on Sat Aug 03 23:23:36 CST 2019.
    -->
    update Bitter
    set id = #{record.id,jdbcType=INTEGER},
      username = #{record.username,jdbcType=VARCHAR},
      password = #{record.password,jdbcType=VARCHAR},
      first_name = #{record.firstName,jdbcType=VARCHAR},
      last_name = #{record.lastName,jdbcType=VARCHAR},
      email = #{record.email,jdbcType=VARCHAR}
    <if test="_parameter != null">
      <include refid="Update_By_Example_Where_Clause" />
    </if>
  </update>
  <update id="updateByPrimaryKeySelective" parameterType="mbg.model.Bitter">
    <!--
      WARNING - @mbggenerated
      This element is automatically generated by MyBatis Generator, do not modify.
      This element was generated on Sat Aug 03 23:23:36 CST 2019.
    -->
    update Bitter
    <set>
      <if test="username != null">
        username = #{username,jdbcType=VARCHAR},
      </if>
      <if test="password != null">
        password = #{password,jdbcType=VARCHAR},
      </if>
      <if test="firstName != null">
        first_name = #{firstName,jdbcType=VARCHAR},
      </if>
      <if test="lastName != null">
        last_name = #{lastName,jdbcType=VARCHAR},
      </if>
      <if test="email != null">
        email = #{email,jdbcType=VARCHAR},
      </if>
    </set>
    where id = #{id,jdbcType=INTEGER}
  </update>
  <update id="updateByPrimaryKey" parameterType="mbg.model.Bitter">
    <!--
      WARNING - @mbggenerated
      This element is automatically generated by MyBatis Generator, do not modify.
      This element was generated on Sat Aug 03 23:23:36 CST 2019.
    -->
    update Bitter
    set username = #{username,jdbcType=VARCHAR},
      password = #{password,jdbcType=VARCHAR},
      first_name = #{firstName,jdbcType=VARCHAR},
      last_name = #{lastName,jdbcType=VARCHAR},
      email = #{email,jdbcType=VARCHAR}
    where id = #{id,jdbcType=INTEGER}
  </update>
</mapper>